digital_eval/__init__.py
digital_eval/cli.py
digital_eval/evaluation.py
digital_eval/geometry.py
digital_eval/metrics.py
digital_eval/preprocessing.py
digital_eval/resolve.py
digital_eval/dictionary_metrics/__init__.py
digital_eval/dictionary_metrics/common.py
digital_eval/dictionary_metrics/language_tool/LanguageTool.py
digital_eval/dictionary_metrics/language_tool/Util.py
digital_eval/dictionary_metrics/language_tool/__init__.py
digital_eval/dictionary_metrics/language_tool/common.py
digital_eval/model/__init__.py
digital_eval/model/common.py
digital_eval/model/digital_object_model.py
digital_eval/model/digital_object_util.py
digital_eval/model/filter.py
digital_eval/model/format_alto_v3_util.py
digital_eval/model/format_page_util.py
digital_eval/model/main.py
digital_eval/model/minidom_util.py
digital_eval-1.9.1.dist-info/licenses/LICENSE
ocr_util/__init__.py
ocr_util/cli.py
digital_eval-1.9.1.dist-info/METADATA
digital_eval-1.9.1.dist-info/WHEEL
digital_eval-1.9.1.dist-info/entry_points.txt
digital_eval-1.9.1.dist-info/top_level.txt
digital_eval-1.9.1.dist-info/RECORD
