Metadata-Version: 2.4
Name: digital-eval
Version: 1.9.1
Summary: Evaluate Digitalization Data
Author-email: Universitäts- und Landesbibliothek Sachsen-Anhalt <development@bibliothek.uni-halle.de>
Project-URL: Homepage, https://github.com/ulb-sachsen-anhalt/digital-eval
Classifier: Programming Language :: Python :: 3
Classifier: License :: OSI Approved :: MIT License
Requires-Python: >=3.10
License-File: LICENSE
Requires-Dist: rapidfuzz>3
Requires-Dist: nltk
Requires-Dist: requests
Requires-Dist: docker
Requires-Dist: numpy
Requires-Dist: shapely
Dynamic: license-file
